graphitesend/__init__.py
graphitesend/block_metric.py
graphitesend/formatter.py
graphitesend/graphitesend.py
graphitesender-0.11.2.dist-info/LICENSE.txt
graphitesender-0.11.2.dist-info/METADATA
graphitesender-0.11.2.dist-info/WHEEL
graphitesender-0.11.2.dist-info/entry_points.txt
graphitesender-0.11.2.dist-info/top_level.txt
graphitesender-0.11.2.dist-info/RECORD
